{
    "name": "Aquatint",
    "patterns": {
        "PxrStylizedControl": {
            "node": "PxrStylizedControl",
            "params": {
                "lineThickness": {
                    "type": "float",
                    "value": 2.0
                }
            }
        }
    },
    "display_filters": {
        "rman_Aquatint_hatching": {
            "node": "PxrStylizedHatching",
            "params": {
                "hatchingTex1": {
                    "type": "string",
                    "value": "StylizedLooks/pxrStylized-aquatint/pxrStylized-aquatint-01.tex"
                },
                "hatchingTex2": {
                    "type": "string",
                    "value": "StylizedLooks/pxrStylized-aquatint/pxrStylized-aquatint-02.tex"
                },
                "hatchingTex3": {
                    "type": "string",
                    "value": "StylizedLooks/pxrStylized-aquatint/pxrStylized-aquatint-03.tex"
                },
                "hatchingTex4": {
                    "type": "string",
                    "value": "StylizedLooks/pxrStylized-aquatint/pxrStylized-aquatint-04.tex"
                },
                "hatchingTex5": {
                    "type": "string",
                    "value": "StylizedLooks/pxrStylized-aquatint/pxrStylized-aquatint-05.tex"
                },
                "hatchingTex6": {
                    "type": "string",
                    "value": "StylizedLooks/pxrStylized-aquatint/pxrStylized-aquatint-06.tex"
                },
                "hatchingTex7": {
                    "type": "string",
                    "value": "StylizedLooks/pxrStylized-aquatint/pxrStylized-aquatint-07.tex"
                },
                "hatchingTex8": {
                    "type": "string",
                    "value": "StylizedLooks/pxrStylized-aquatint/pxrStylized-aquatint-08.tex"
                },
                "visualizer": {
                    "type": "string",
                    "value": "hatchingOnColor"
                }                
            }
        },
        "rman_Aquatint_lines": {
            "node": "PxrStylizedLines",
            "params": {
                "lineThickness": {
                    "type": "float",
                    "value": 2.0
                }
            }            
        }

    }
}